neoxin_core/__init__.py
neoxin_core/cache/__init__.py
neoxin_core/cache/base.py
neoxin_core/cache/config.py
neoxin_core/cache/file.py
neoxin_core/cache/memory.py
neoxin_core/cache/README.md
neoxin_core/cache/redis_cache.py
neoxin_core/cache/stores.py
neoxin_core/db.py
neoxin_core/decorators.py
neoxin_core/dependencies.py
neoxin_core/http.py
neoxin_core/logging.py
neoxin_core/module.py
neoxin_core/plugin.py
neoxin_core/schemas.py
neoxin_core/security.py
neoxin_core/settings.py
neoxin_core/storage/__init__.py
neoxin_core/storage/aliyun.py
neoxin_core/storage/base.py
neoxin_core/storage/local.py
neoxin_core/storage/manager.py
neoxin_core/storage/qiniu.py
neoxin_core/storage/tencent.py
neoxin_core-0.0.2.dist-info/licenses/LICENSE
neoxin_core-0.0.2.dist-info/METADATA
neoxin_core-0.0.2.dist-info/WHEEL
neoxin_core-0.0.2.dist-info/RECORD
