Metadata-Version: 2.4
Name: neoxin-core
Version: 0.0.2
Summary: A Core Implementation Library Based on the FastAPI framework
License: MIT
License-File: LICENSE
Author: amiko
Author-email: caihaifei@foxmail.com
Requires-Python: >=3.12
Classifier: Development Status :: 2 - Pre-Alpha
Classifier: Intended Audience :: Developers
Classifier: License :: OSI Approved :: MIT License
Classifier: Operating System :: OS Independent
Classifier: Programming Language :: Python
Classifier: Programming Language :: Python :: 3
Classifier: Programming Language :: Python :: 3.12
Classifier: Topic :: Software Development :: Libraries :: Python Modules
Requires-Dist: bcrypt (>=5.0.0,<6.0.0)
Requires-Dist: cffi (==2.0)
Requires-Dist: cos-python-sdk-v5 (>=1.9.40,<2.0.0)
Requires-Dist: fastapi (>=0.125.0,<0.126.0)
Requires-Dist: oss2 (>=2.19.1,<3.0.0)
Requires-Dist: pydantic (>=2.12.5,<3.0.0)
Requires-Dist: pydantic-settings (>=2.12.0,<3.0.0)
Requires-Dist: pyjwt (>=2.10.1,<3.0.0)
Requires-Dist: pymysql (>=1.1.2,<2.0.0)
Requires-Dist: qiniu (>=7.17.0,<8.0.0)
Requires-Dist: redis (>=7.1.0,<8.0.0)
Requires-Dist: sqlalchemy (>=2.0.45,<3.0.0)
Project-URL: Homepage, https://gitee.com/neo-xin/neo-core
Project-URL: Issues, https://gitee.com/neo-xin/neo-core/issues
